README.md
setup.py
bin/haveibeenpwned
haveibeenpwned/__about__.py
haveibeenpwned/__init__.py
haveibeenpwned/status.py
haveibeenpwned.egg-info/PKG-INFO
haveibeenpwned.egg-info/SOURCES.txt
haveibeenpwned.egg-info/dependency_links.txt
haveibeenpwned.egg-info/not-zip-safe
haveibeenpwned.egg-info/requires.txt
haveibeenpwned.egg-info/top_level.txt