Metadata-Version: 2.1
Name: haveibeenpwned
Version: 0.0.4
Summary: PyPi quick status implementation for the awesome haveibeenpwned.com service
Home-page: https://github.com/marinko-peso/haveibeenpwned/
Author: Marinko Peso
Author-email: marinko.peso@gmail.com
License: MIT
Keywords: haveibeenpwned email breached status security
Platform: UNKNOWN
Classifier: Intended Audience :: Developers
Classifier: License :: OSI Approved :: MIT License
Classifier: Operating System :: OS Independent
Classifier: Programming Language :: Python
Classifier: Programming Language :: Python :: 2
Classifier: Programming Language :: Python :: 2.7
Classifier: Programming Language :: Python :: 3
Classifier: Programming Language :: Python :: 3.6
